[
  {
    "timestamp": "2026-03-30T18:11:21.3290385Z",
    "runId": 23758867136,
    "coverage": 31.59,
    "obligations": 244023,
    "met": 77095,
    "lines": 132918,
    "perFlag": {
      "unit": 60.89,
      "integration": 26.93,
      "guard": 5.8,
      "property": 8.44,
      "contract": 1.45
    }
  },
  {
    "timestamp": "2026-03-30T19:40:31.4066813Z",
    "runId": 23762714875,
    "coverage": 31.61,
    "obligations": 243892,
    "met": 77089,
    "lines": 132982,
    "perFlag": {
      "unit": 60.97,
      "integration": 26.92,
      "guard": 5.8,
      "property": 8.44,
      "contract": 1.45
    }
  },
  {
    "timestamp": "2026-03-30T21:19:57.8951142Z",
    "runId": 23767041850,
    "coverage": 31.61,
    "obligations": 243967,
    "met": 77111,
    "lines": 132956,
    "perFlag": {
      "unit": 60.88,
      "integration": 26.95,
      "guard": 5.84,
      "property": 8.44,
      "contract": 1.45
    }
  },
  {
    "timestamp": "2026-03-31T08:21:20.0123043Z",
    "runId": 23786420469,
    "coverage": 32.12,
    "obligations": 240512,
    "met": 77251,
    "lines": 133002,
    "perFlag": {
      "unit": 60.94,
      "guard": 5.84,
      "contract": 1.24,
      "integration": 29.72,
      "property": 10.1
    }
  },
  {
    "timestamp": "2026-03-31T10:34:56.7413825Z",
    "runId": 23791771278,
    "coverage": 32.13,
    "obligations": 240535,
    "met": 77283,
    "lines": 133052,
    "perFlag": {
      "unit": 60.98,
      "guard": 5.84,
      "contract": 1.24,
      "integration": 29.66,
      "property": 10.61
    }
  },
  {
    "timestamp": "2026-03-31T11:11:48.7100553Z",
    "runId": 23793138363,
    "coverage": 32.12,
    "obligations": 240555,
    "met": 77265,
    "lines": 133008,
    "perFlag": {
      "unit": 60.94,
      "guard": 5.84,
      "contract": 1.24,
      "integration": 29.68,
      "property": 10.45
    }
  }
]