{
  "package": "Encina.GuardClauses",
  "generated": "2026-03-27T12:05:17Z",
  "totalFiles": 2,
  "targets": {
    "guard": 15,
    "unit": 60,
    "integration": 0,
    "property": 87.0
  },
  "files": {
    "GlobalSuppressions.cs": {
      "defaultTests": [],
      "defaultRule": "GlobalSuppressions.cs",
      "reason": "Only [SuppressMessage] attributes"
    },
    "Guards.cs": {
      "defaultTests": [
        "unit",
        "guard"
      ],
      "defaultRule": "*.cs",
      "reason": "Default: assume testable with mocks"
    }
  }
}
